{
    "Variables": {
        "User Stake Amount": [
            "UserInfo.amount"
        ],
        "User Stake Reward": [
            "UserInfo.rewardDebt"
        ],
        "User Stake Time": [],
        "Stake Token Address": [
            "PoolInfo.lpToken"
        ],
        "Reward Token Address": [
            "dough",
            "jelly"
        ]
    },
    "Calculations": {
        "Stake": [
            {
                "Function": "enterStaking",
                "Node": "pool.lpToken.safeTransferFrom(address(msg.sender), address(this), _amount)"
            },
            {
                "Function": "deposit",
                "Node": "pool.lpToken.safeTransferFrom(address(msg.sender), address(this), _amount)"
            }
        ],
        "getReward": [
            {
                "Function": "enterStaking",
                "Node": "safeDoughTransfer(msg.sender, pending)"
            },
            {
                "Function": "deposit",
                "Node": "safeDoughTransfer(msg.sender, pending)"
            },
            {
                "Function": "withdraw",
                "Node": "safeDoughTransfer(msg.sender, pending)"
            },
            {
                "Function": "leaveStaking",
                "Node": "safeDoughTransfer(msg.sender, pending)"
            }
        ],
        "unStake": [
            {
                "Function": "withdraw",
                "Node": "pool.lpToken.safeTransfer(address(msg.sender), _amount)"
            },
            {
                "Function": "leaveStaking",
                "Node": "pool.lpToken.safeTransfer(address(msg.sender), _amount)"
            },
            {
                "Function": "emergencyWithdraw",
                "Node": "pool.lpToken.safeTransfer(address(msg.sender), user.amount)"
            }
        ]
    }
}