{
    "Variables": {
        "User Stake Amount": [
            "_balances"
        ],
        "User Stake Reward": [],
        "User Stake Time": [],
        "Stake Token Address": [],
        "Reward Token Address": []
    },
    "Functions": {
        "Stake": [
            "stake"
        ],
        "getReward": [
            "withdrawStake"
        ],
        "unStake": [
            "withdrawStake"
        ],
        "Sensitive Functions": []
    },
    "Calculations": {
        "Stake": [
            {
                "Function": "stake",
                "Node": [
                    334
                ],
                "Input": [
                    "_amount"
                ],
                "Calculation Variables": [],
                "Control Variables": [],
                "Full Calculation Variables": [],
                "Is Depend on this.balance": false
            }
        ],
        "getReward": [
            {
                "Function": "withdrawStake",
                "Node": [
                    374
                ],
                "Input": [
                    "amount",
                    "stake_index"
                ],
                "Calculation Variables": [],
                "Control Variables": [],
                "Full Calculation Variables": [],
                "Is Depend on this.balance": false
            }
        ],
        "unStake": [
            {
                "Function": "withdrawStake",
                "Node": [
                    387
                ],
                "Input": [
                    "amount",
                    "stake_index"
                ],
                "Calculation Variables": [],
                "Control Variables": [],
                "Full Calculation Variables": [],
                "Is Depend on this.balance": false
            }
        ]
    }
}