{
    "Variables": {
        "User Stake Amount": [
            "totalSupply"
        ],
        "User Stake Reward": [],
        "User Stake Time": [],
        "Stake Token Address": [
            "underlying"
        ],
        "Reward Token Address": []
    },
    "Functions": {
        "Stake": [],
        "getReward": [],
        "unStake": [],
        "Sensitive Functions": [
            "initialize",
            "initialize",
            "swapLPToken"
        ]
    },
    "Calculations": {
        "Stake": [],
        "getReward": [],
        "unStake": []
    }
}