{
    "Variables": {
        "User Stake Amount": [],
        "User Stake Reward": [],
        "User Stake Time": [],
        "Stake Token Address": [
            "usdc_dodo_lp_token"
        ],
        "Reward Token Address": [
            "dodo"
        ]
    },
    "Functions": {
        "Stake": [
            "deposit",
            "deposit"
        ],
        "getReward": [
            "harvest",
            "harvest"
        ],
        "unStake": [
            "withdraw",
            "withdrawAll",
            "withdrawForSwap"
        ],
        "Sensitive Functions": []
    },
    "Calculations": {
        "Stake": [
            {
                "Function": "deposit",
                "Node": [
                    1646
                ],
                "Input": [],
                "Calculation Variables": [],
                "Control Variables": [
                    "rewards",
                    "want"
                ],
                "Full Calculation Variables": [
                    "rewards",
                    "want"
                ],
                "Is Depend on this.balance": true
            }
        ],
        "getReward": [
            {
                "Function": "harvest",
                "Node": [
                    1677
                ],
                "Input": [
                    "callFeeRecipient"
                ],
                "Calculation Variables": [
                    "native"
                ],
                "Control Variables": [
                    "usdc_dodo_lp_token",
                    "native",
                    "dodo",
                    "usdc",
                    "strategist",
                    "matic_destination",
                    "governance",
                    "keeper",
                    "harvesters",
                    "rewards"
                ],
                "Full Calculation Variables": [
                    "usdc_dodo_lp_token",
                    "native",
                    "dodo",
                    "usdc",
                    "strategist",
                    "matic_destination",
                    "governance",
                    "keeper",
                    "harvesters",
                    "rewards"
                ],
                "Is Depend on this.balance": true
            }
        ],
        "unStake": [
            {
                "Function": "withdrawAll",
                "Node": [
                    1655
                ],
                "Input": [
                    "_amount"
                ],
                "Calculation Variables": [],
                "Control Variables": [
                    "rewards"
                ],
                "Full Calculation Variables": [
                    "rewards"
                ],
                "Is Depend on this.balance": false
            },
            {
                "Function": "withdrawForSwap",
                "Node": [
                    1655
                ],
                "Input": [
                    "_amount"
                ],
                "Calculation Variables": [],
                "Control Variables": [
                    "rewards"
                ],
                "Full Calculation Variables": [
                    "rewards"
                ],
                "Is Depend on this.balance": false
            },
            {
                "Function": "withdraw",
                "Node": [
                    1655
                ],
                "Input": [
                    "_amount"
                ],
                "Calculation Variables": [],
                "Control Variables": [
                    "rewards"
                ],
                "Full Calculation Variables": [
                    "rewards"
                ],
                "Is Depend on this.balance": false
            }
        ]
    }
}