{
    "Variables": {
        "User Stake Amount": [
            "balanceOf"
        ],
        "User Stake Reward": [
            "rewards"
        ],
        "User Stake Time": [
            "duration"
        ],
        "Stake Token Address": [
            "loveLP"
        ],
        "Reward Token Address": [
            "biffysLove"
        ]
    },
    "Calculations": {
        "Stake": [
            {
                "Function": "stake",
                "Node": "super.stake(amount)"
            }
        ],
        "getReward": [
            {
                "Function": "getReward",
                "Node": "biffysLove.transfer(msg.sender, reward)"
            }
        ],
        "unStake": []
    }
}