{
    "Variables": {
        "User Stake Amount": [],
        "User Stake Reward": [],
        "User Stake Time": [],
        "Stake Token Address": [
            "hugsPool",
            "c2pool"
        ],
        "Reward Token Address": [
            "stakingRewards"
        ]
    },
    "Functions": {
        "Stake": [],
        "getReward": [
            "calWithdrawAndEarned",
            "getStakingInfo"
        ],
        "unStake": [
            "calWithdrawAndEarned",
            "getStakingInfo"
        ],
        "Sensitive Functions": []
    },
    "Calculations": {
        "Stake": [],
        "getReward": [
            {
                "Function": "calWithdrawAndEarned",
                "Node": [
                    157
                ],
                "Input": [
                    "wallet"
                ],
                "Calculation Variables": [],
                "Control Variables": [
                    "c2pool",
                    "hugsPool",
                    "stakingRewards"
                ],
                "Full Calculation Variables": [
                    "c2pool",
                    "hugsPool",
                    "stakingRewards"
                ],
                "Is Depend on this.balance": false
            },
            {
                "Function": "getStakingInfo",
                "Node": [
                    160
                ],
                "Input": [
                    "wallet",
                    "amount",
                    "wallet"
                ],
                "Calculation Variables": [],
                "Control Variables": [
                    "hugsPool",
                    "c2pool",
                    "stakingRewards"
                ],
                "Full Calculation Variables": [
                    "hugsPool",
                    "c2pool",
                    "stakingRewards"
                ],
                "Is Depend on this.balance": false
            }
        ],
        "unStake": [
            {
                "Function": "calWithdrawAndEarned",
                "Node": [
                    162
                ],
                "Input": [
                    "wallet"
                ],
                "Calculation Variables": [],
                "Control Variables": [
                    "hugsPool",
                    "c2pool",
                    "stakingRewards"
                ],
                "Full Calculation Variables": [
                    "hugsPool",
                    "c2pool",
                    "stakingRewards"
                ],
                "Is Depend on this.balance": false
            },
            {
                "Function": "getStakingInfo",
                "Node": [
                    162
                ],
                "Input": [
                    "wallet"
                ],
                "Calculation Variables": [],
                "Control Variables": [
                    "hugsPool",
                    "c2pool",
                    "stakingRewards"
                ],
                "Full Calculation Variables": [
                    "hugsPool",
                    "c2pool",
                    "stakingRewards"
                ],
                "Is Depend on this.balance": false
            }
        ]
    }
}