{
    "Variables": {
        "User Stake Amount": [],
        "User Stake Reward": [],
        "User Stake Time": [
            "lastHarvest"
        ],
        "Stake Token Address": [
            "want"
        ],
        "Reward Token Address": [
            "output"
        ]
    },
    "Functions": {
        "Stake": [
            "beforeDeposit",
            "deposit",
            "harvest",
            "harvest",
            "unpause"
        ],
        "getReward": [
            "beforeDeposit",
            "harvest",
            "harvest"
        ],
        "unStake": [
            "panic",
            "retireStrat",
            "withdraw"
        ],
        "Sensitive Functions": []
    },
    "Calculations": {
        "Stake": [
            {
                "Function": "deposit",
                "Node": [
                    1467
                ],
                "Input": [],
                "Calculation Variables": [],
                "Control Variables": [
                    "_paused",
                    "rewardPool",
                    "want"
                ],
                "Full Calculation Variables": [
                    "_paused",
                    "rewardPool",
                    "want"
                ],
                "Is Depend on this.balance": true
            },
            {
                "Function": "harvest",
                "Node": [
                    1467
                ],
                "Input": [],
                "Calculation Variables": [],
                "Control Variables": [
                    "_paused",
                    "rewardPool",
                    "want"
                ],
                "Full Calculation Variables": [
                    "_paused",
                    "rewardPool",
                    "want"
                ],
                "Is Depend on this.balance": true
            },
            {
                "Function": "beforeDeposit",
                "Node": [
                    1467
                ],
                "Input": [],
                "Calculation Variables": [],
                "Control Variables": [
                    "_paused",
                    "rewardPool",
                    "want"
                ],
                "Full Calculation Variables": [
                    "_paused",
                    "rewardPool",
                    "want"
                ],
                "Is Depend on this.balance": true
            },
            {
                "Function": "harvest",
                "Node": [
                    1467
                ],
                "Input": [],
                "Calculation Variables": [],
                "Control Variables": [
                    "_paused",
                    "rewardPool",
                    "want"
                ],
                "Full Calculation Variables": [
                    "_paused",
                    "rewardPool",
                    "want"
                ],
                "Is Depend on this.balance": true
            },
            {
                "Function": "unpause",
                "Node": [
                    1467
                ],
                "Input": [],
                "Calculation Variables": [],
                "Control Variables": [
                    "_paused",
                    "rewardPool",
                    "want"
                ],
                "Full Calculation Variables": [
                    "_paused",
                    "rewardPool",
                    "want"
                ],
                "Is Depend on this.balance": true
            }
        ],
        "getReward": [
            {
                "Function": "harvest",
                "Node": [
                    1543
                ],
                "Input": [
                    "callFeeRecipient",
                    "callFeeRecipient"
                ],
                "Calculation Variables": [
                    "native",
                    "output",
                    "beefyFeeConfig",
                    "DIVISOR"
                ],
                "Control Variables": [
                    "native",
                    "output",
                    "beefyFeeConfig",
                    "beefyFeeRecipient",
                    "strategist",
                    "rewardPool",
                    "DIVISOR",
                    "_paused"
                ],
                "Full Calculation Variables": [
                    "native",
                    "output",
                    "beefyFeeConfig",
                    "beefyFeeRecipient",
                    "strategist",
                    "rewardPool",
                    "DIVISOR",
                    "_paused"
                ],
                "Is Depend on this.balance": true
            },
            {
                "Function": "beforeDeposit",
                "Node": [
                    1543
                ],
                "Input": [
                    "callFeeRecipient",
                    "callFeeRecipient"
                ],
                "Calculation Variables": [
                    "native",
                    "output",
                    "beefyFeeConfig",
                    "DIVISOR"
                ],
                "Control Variables": [
                    "native",
                    "output",
                    "beefyFeeConfig",
                    "beefyFeeRecipient",
                    "strategist",
                    "rewardPool",
                    "DIVISOR",
                    "_paused"
                ],
                "Full Calculation Variables": [
                    "native",
                    "output",
                    "beefyFeeConfig",
                    "beefyFeeRecipient",
                    "strategist",
                    "rewardPool",
                    "DIVISOR",
                    "_paused"
                ],
                "Is Depend on this.balance": true
            },
            {
                "Function": "harvest",
                "Node": [
                    1543
                ],
                "Input": [
                    "callFeeRecipient",
                    "callFeeRecipient"
                ],
                "Calculation Variables": [
                    "native",
                    "output",
                    "beefyFeeConfig",
                    "DIVISOR"
                ],
                "Control Variables": [
                    "native",
                    "output",
                    "beefyFeeConfig",
                    "beefyFeeRecipient",
                    "strategist",
                    "rewardPool",
                    "DIVISOR",
                    "_paused"
                ],
                "Full Calculation Variables": [
                    "native",
                    "output",
                    "beefyFeeConfig",
                    "beefyFeeRecipient",
                    "strategist",
                    "rewardPool",
                    "DIVISOR",
                    "_paused"
                ],
                "Is Depend on this.balance": true
            }
        ],
        "unStake": [
            {
                "Function": "withdraw",
                "Node": [
                    1491
                ],
                "Input": [
                    "_amount"
                ],
                "Calculation Variables": [
                    "withdrawalFee",
                    "WITHDRAWAL_MAX",
                    "want"
                ],
                "Control Variables": [
                    "rewardPool",
                    "want",
                    "WITHDRAWAL_MAX",
                    "vault",
                    "withdrawalFee"
                ],
                "Full Calculation Variables": [
                    "rewardPool",
                    "want",
                    "WITHDRAWAL_MAX",
                    "vault",
                    "withdrawalFee"
                ],
                "Is Depend on this.balance": true
            },
            {
                "Function": "retireStrat",
                "Node": [
                    1619
                ],
                "Input": [],
                "Calculation Variables": [
                    "want"
                ],
                "Control Variables": [
                    "rewardPool",
                    "want",
                    "vault"
                ],
                "Full Calculation Variables": [
                    "rewardPool",
                    "want",
                    "vault"
                ],
                "Is Depend on this.balance": true
            },
            {
                "Function": "panic",
                "Node": [
                    1625
                ],
                "Input": [],
                "Calculation Variables": [],
                "Control Variables": [
                    "_owner",
                    "keeper",
                    "rewardPool"
                ],
                "Full Calculation Variables": [
                    "_owner",
                    "keeper",
                    "rewardPool"
                ],
                "Is Depend on this.balance": false
            }
        ]
    }
}